[{"pk": "23166162769", "model": "core.cliente", "fields": {"razon_social": "SCHANZ EDUARDO OSCAR", "ciudad": 1, "direccion": "GALINA 156"}}, {"pk": "30709635073", "model": "core.cliente", "fields": {"razon_social": "TECHNICAL COMPUTERS S.R.L.", "ciudad": 1, "direccion": "PARAGUAY 52"}}, {"pk": "33709032149", "model": "core.cliente", "fields": {"razon_social": "AXIS S.R.L", "ciudad": 1, "direccion": "PJE. SAN JUAN 290"}}, {"pk": "30670564629", "model": "core.cliente", "fields": {"razon_social": "SET COMPUTACION", "ciudad": 2, "direccion": "GALES 46"}}, {"pk": "30646037391", "model": "core.cliente", "fields": {"razon_social": "COMPUCENTER", "ciudad": 3, "direccion": "ROCA 777"}}]
